{
    "_id": "C2bde7gl3e573v7O",
    "name": "Trained Predator",
    "type": "feat",
    "img": "systems/pf2e/icons/features/feats/feats.webp",
    "data": {
        "description": {
            "value": "<p>You become proficient in Stealth and Perception. If you were already trained in either, you become proficient in any other skill.</p>"
        },
        "source": { "value": "Ponyfinder: Second Edition Conversion Guide" },
        "traits": { "value": ["hb_sun-cat"], "rarity": "common", "custom": "" },
        "rules": [],
        "level": { "value": 5 },
        "featType": { "value": "ancestry" },
        "onlyLevel1": false,
        "maxTakable": 1,
        "actionType": { "value": "passive" },
        "actionCategory": { "value": "" },
        "actions": { "value": null },
        "prerequisites": { "value": [] },
        "location": null
    }
}
